aural/erb.py
aural/feature.py
aural/iso226.py
aural/meridian.py
aural/segment.py
aural/weight.py
aural/young.py
aural_features-1.0.0.data/scripts/moby_extract_calls.py
aural_features-1.0.0.data/scripts/plot_isolation.py
aural_features-1.0.0.data/scripts/temporal_features.py
aural_features-1.0.0.dist-info/LICENSE
aural_features-1.0.0.dist-info/METADATA
aural_features-1.0.0.dist-info/WHEEL
aural_features-1.0.0.dist-info/top_level.txt
aural_features-1.0.0.dist-info/RECORD
